Counter.v
module up_counter(input clk, reset, output[3:0] counter);
    reg [3:0] counter_up;                           // Initialise register counter_up to find up counter states
    always @(posedge clk or posedge reset)          // Postive edge triggered circuit
    begin
        if(reset)
            begin
                counter_up = 4'd0;                  // If reset==1, set counter to 0000
            end
        else
            begin
                counter_up = counter_up + 4'd1;     // Else, add 0001 to counter
            end       
    end 
    assign counter = counter_up;                    // Return new value of counter
endmodule

module down_counter(input clk, reset, output [3:0] counter);
    reg [3:0] counter_down;                         // Initialise register counter_down to find down counter states
    always @(posedge clk or posedge reset)          // Postive edge triggered circuit
    begin
        if(reset)
            begin
                counter_down = 4'hf;                // If reset==1, set counter to 1111
            end
        else
            begin
                counter_down = counter_down - 4'd1; // Else, subtract 0001 from counter
            end                                     
    end 
    assign counter = counter_down;                  // Return new value of counter
endmodule

CounterTB.v
module counter_testbench();
    reg clk, reset;
    wire [3:0] counter1,counter2;

    up_counter up(clk, reset, counter1);
    down_counter down(clk, reset, counter2);

    initial begin
        $dumpfile("Counter.vcd");
        $dumpvars(0,counter_testbench);
    end
    initial begin 
        clk=0;
        repeat(96) 
            #5 clk=~clk;
    end
    initial begin
        reset = 1;
        #10
        reset = 0;
    end
endmodule

Counter.vcd
$date
	Mon Nov 25 13:16:42 2019
$end
$version
	Icarus Verilog
$end
$timescale
	1s
$end
$scope module counter_testbench $end
$var wire 4 ! counter2 [3:0] $end
$var wire 4 " counter1 [3:0] $end
$var reg 1 # clk $end
$var reg 1 $ reset $end
$scope module down $end
$var wire 1 # clk $end
$var wire 4 % counter [3:0] $end
$var wire 1 $ reset $end
$var reg 4 & counter_down [3:0] $end
$upscope $end
$scope module up $end
$var wire 1 # clk $end
$var wire 4 ' counter [3:0] $end
$var wire 1 $ reset $end
$var reg 4 ( counter_up [3:0] $end
$upscope $end
$upscope $end
$enddefinitions $end
#0
$dumpvars
b0 (
b0 '
b1111 &
b1111 %
1$
0#
b0 "
b1111 !
$end
#5
1#
#10
0#
0$
#15
b1 "
b1 '
b1 (
b1110 !
b1110 %
b1110 &
1#
#20
0#
#25
b1101 !
b1101 %
b1101 &
b10 "
b10 '
b10 (
1#
#30
0#
#35
b11 "
b11 '
b11 (
b1100 !
b1100 %
b1100 &
1#
#40
0#
#45
b1011 !
b1011 %
b1011 &
b100 "
b100 '
b100 (
1#
#50
0#
#55
b101 "
b101 '
b101 (
b1010 !
b1010 %
b1010 &
1#
#60
0#
#65
b1001 !
b1001 %
b1001 &
b110 "
b110 '
b110 (
1#
#70
0#
#75
b111 "
b111 '
b111 (
b1000 !
b1000 %
b1000 &
1#
#80
0#
#85
b111 !
b111 %
b111 &
b1000 "
b1000 '
b1000 (
1#
#90
0#
#95
b1001 "
b1001 '
b1001 (
b110 !
b110 %
b110 &
1#
#100
0#
#105
b101 !
b101 %
b101 &
b1010 "
b1010 '
b1010 (
1#
#110
0#
#115
b1011 "
b1011 '
b1011 (
b100 !
b100 %
b100 &
1#
#120
0#
#125
b11 !
b11 %
b11 &
b1100 "
b1100 '
b1100 (
1#
#130
0#
#135
b1101 "
b1101 '
b1101 (
b10 !
b10 %
b10 &
1#
#140
0#
#145
b1 !
b1 %
b1 &
b1110 "
b1110 '
b1110 (
1#
#150
0#
#155
b1111 "
b1111 '
b1111 (
b0 !
b0 %
b0 &
1#
#160
0#
#165
b1111 !
b1111 %
b1111 &
b0 "
b0 '
b0 (
1#
#170
0#
#175
b1 "
b1 '
b1 (
b1110 !
b1110 %
b1110 &
1#
#180
0#
#185
b1101 !
b1101 %
b1101 &
b10 "
b10 '
b10 (
1#
#190
0#
#195
b11 "
b11 '
b11 (
b1100 !
b1100 %
b1100 &
1#
#200
0#
#205
b1011 !
b1011 %
b1011 &
b100 "
b100 '
b100 (
1#
#210
0#
#215
b101 "
b101 '
b101 (
b1010 !
b1010 %
b1010 &
1#
#220
0#
#225
b1001 !
b1001 %
b1001 &
b110 "
b110 '
b110 (
1#
#230
0#
#235
b111 "
b111 '
b111 (
b1000 !
b1000 %
b1000 &
1#
#240
0#
#245
b111 !
b111 %
b111 &
b1000 "
b1000 '
b1000 (
1#
#250
0#
#255
b1001 "
b1001 '
b1001 (
b110 !
b110 %
b110 &
1#
#260
0#
#265
b101 !
b101 %
b101 &
b1010 "
b1010 '
b1010 (
1#
#270
0#
#275
b1011 "
b1011 '
b1011 (
b100 !
b100 %
b100 &
1#
#280
0#
#285
b11 !
b11 %
b11 &
b1100 "
b1100 '
b1100 (
1#
#290
0#
#295
b1101 "
b1101 '
b1101 (
b10 !
b10 %
b10 &
1#
#300
0#
#305
b1 !
b1 %
b1 &
b1110 "
b1110 '
b1110 (
1#
#310
0#
#315
b1111 "
b1111 '
b1111 (
b0 !
b0 %
b0 &
1#
#320
0#
#325
b1111 !
b1111 %
b1111 &
b0 "
b0 '
b0 (
1#
#330
0#
#335
b1 "
b1 '
b1 (
b1110 !
b1110 %
b1110 &
1#
#340
0#
#345
b1101 !
b1101 %
b1101 &
b10 "
b10 '
b10 (
1#
#350
0#
#355
b11 "
b11 '
b11 (
b1100 !
b1100 %
b1100 &
1#
#360
0#
#365
b1011 !
b1011 %
b1011 &
b100 "
b100 '
b100 (
1#
#370
0#
#375
b101 "
b101 '
b101 (
b1010 !
b1010 %
b1010 &
1#
#380
0#
#385
b1001 !
b1001 %
b1001 &
b110 "
b110 '
b110 (
1#
#390
0#
#395
b111 "
b111 '
b111 (
b1000 !
b1000 %
b1000 &
1#
#400
0#
#405
b111 !
b111 %
b111 &
b1000 "
b1000 '
b1000 (
1#
#410
0#
#415
b1001 "
b1001 '
b1001 (
b110 !
b110 %
b110 &
1#
#420
0#
#425
b101 !
b101 %
b101 &
b1010 "
b1010 '
b1010 (
1#
#430
0#
#435
b1011 "
b1011 '
b1011 (
b100 !
b100 %
b100 &
1#
#440
0#
#445
b11 !
b11 %
b11 &
b1100 "
b1100 '
b1100 (
1#
#450
0#
#455
b1101 "
b1101 '
b1101 (
b10 !
b10 %
b10 &
1#
#460
0#
#465
b1 !
b1 %
b1 &
b1110 "
b1110 '
b1110 (
1#
#470
0#
#475
b1111 "
b1111 '
b1111 (
b0 !
b0 %
b0 &
1#
